bridges/ros_bridge/_delete_rviz_line.py
bridges/ros_bridge/ros_socket_server.py
bridges/ros_bridge/src/metadrive_example_bridge/setup.py
bridges/ros_bridge/src/metadrive_example_bridge/launch/metadrive_example_bridge.launch.py
bridges/ros_bridge/src/metadrive_example_bridge/metadrive_example_bridge/__init__.py
bridges/ros_bridge/src/metadrive_example_bridge/metadrive_example_bridge/camera_bridge.py
bridges/ros_bridge/src/metadrive_example_bridge/metadrive_example_bridge/lidar_bridge.py
bridges/ros_bridge/src/metadrive_example_bridge/metadrive_example_bridge/obj_bridge.py
jethro_metadrive-0.5.1.dist-info/licenses/LICENSE.txt
metadrive/__init__.py
metadrive/constants.py
metadrive/pull_asset.py
metadrive/type.py
metadrive/version.py
metadrive/base_class/__init__.py
metadrive/base_class/base_object.py
metadrive/base_class/base_runnable.py
metadrive/base_class/configurable.py
metadrive/base_class/nameable.py
metadrive/base_class/randomizable.py
metadrive/component/__init__.py
metadrive/component/pg_space.py
metadrive/component/algorithm/BIG.py
metadrive/component/algorithm/__init__.py
metadrive/component/algorithm/blocks_prob_dist.py
metadrive/component/block/__init__.py
metadrive/component/block/base_block.py
metadrive/component/buildings/__init__.py
metadrive/component/buildings/base_building.py
metadrive/component/buildings/tollgate_building.py
metadrive/component/lane/__init__.py
metadrive/component/lane/abs_lane.py
metadrive/component/lane/circular_lane.py
metadrive/component/lane/extension_lane.py
metadrive/component/lane/opendrive_lane.py
metadrive/component/lane/pg_lane.py
metadrive/component/lane/point_lane.py
metadrive/component/lane/scenario_lane.py
metadrive/component/lane/straight_lane.py
metadrive/component/map/__init__.py
metadrive/component/map/base_map.py
metadrive/component/map/city_map.py
metadrive/component/map/pg_map.py
metadrive/component/map/scenario_map.py
metadrive/component/navigation_module/__init__.py
metadrive/component/navigation_module/base_navigation.py
jethro_metadrive-0.5.1.dist-info/METADATA
jethro_metadrive-0.5.1.dist-info/WHEEL
jethro_metadrive-0.5.1.dist-info/top_level.txt
jethro_metadrive-0.5.1.dist-info/RECORD
