Metadata-Version: 2.4
Name: jethro-metadrive
Version: 0.5.1
Summary: the fork of metadrive
Requires-Python: <3.13,>=3.11
License-File: LICENSE.txt
Requires-Dist: filelock>=3.19.1
Requires-Dist: gymnasium>=1.2.1
Requires-Dist: lxml>=6.0.2
Requires-Dist: matplotlib>=3.10.6
Requires-Dist: mediapy>=1.2.4
Requires-Dist: numpy>=2.3.3
Requires-Dist: opencv-python>=4.11.0.86
Requires-Dist: panda3d>=1.10.15
Requires-Dist: panda3d-gltf>=1.3.0
Requires-Dist: pillow>=11.3.0
Requires-Dist: progressbar>=2.5
Requires-Dist: psutil>=7.1.0
Requires-Dist: pygame>=2.6.1
Requires-Dist: pygments>=2.19.2
Requires-Dist: requests>=2.32.5
Requires-Dist: shapely>=2.1.2
Requires-Dist: tqdm>=4.67.1
Requires-Dist: yapf>=0.43.0
Provides-Extra: cuda
Requires-Dist: cuda-python==12.1.0; extra == "cuda"
Requires-Dist: PyOpenGL==3.1.6; extra == "cuda"
Requires-Dist: PyOpenGL-accelerate==3.1.6; extra == "cuda"
Requires-Dist: pyrr==0.10.3; extra == "cuda"
Requires-Dist: glfw; extra == "cuda"
Provides-Extra: gym
Requires-Dist: gym>=0.26.2; extra == "gym"
Provides-Extra: ros
Requires-Dist: zmq>=0.0.0; extra == "ros"
Dynamic: license-file
